azimpy/__init__.py
azimpy/orientation.py
azimpy/params.py
azimpy/plot.py
azimpy/rstats.py
azimpy/utils.py
azimpy/version/__init__.py
AzimPy-0.2.0.dist-info/LICENSE
AzimPy-0.2.0.dist-info/METADATA
AzimPy-0.2.0.dist-info/WHEEL
AzimPy-0.2.0.dist-info/top_level.txt
AzimPy-0.2.0.dist-info/RECORD
