Metadata-Version: 2.1
Name: AzimPy
Version: 0.2.0
Summary: Estimate OBS sensor orientation
Author: Yasunori Sawaki
License: MIT License
Keywords: seismology,ocean bottom seismograph,Rayleigh wave,marine seismology
Classifier: Programming Language :: Python :: 3 :: Only
Classifier: Programming Language :: Python :: 3.8
Classifier: Programming Language :: Python :: 3.9
Classifier: Programming Language :: Python :: 3.10
Classifier: Topic :: Scientific/Engineering :: Physics
Classifier: Operating System :: POSIX :: Linux
Classifier: License :: OSI Approved :: MIT License
Requires-Python: >=3.8
License-File: LICENSE
Requires-Dist: obspy (>=1.3)
Requires-Dist: astropy (>=5.0)
Requires-Dist: matplotlib (>=3.5)
Requires-Dist: scipy (>=1.4)
Requires-Dist: pandas
Requires-Dist: numpy
Requires-Dist: tqdm
